makefortune_lib/__init__.py
makefortune_lib/comm_lib/__init__.py
makefortune_lib/comm_lib/ipc/__init__.py
makefortune_lib/comm_lib/ipc/queueManager.py
makefortune_lib/comm_lib/plc_comm/__init__.py
makefortune_lib/comm_lib/plc_comm/CIP/__init__.py
makefortune_lib/comm_lib/plc_comm/CIP/cip.py
makefortune_lib/comm_lib/plc_comm/FINS/FINS.py
makefortune_lib/comm_lib/plc_comm/FINS/__init__.py
makefortune_lib/comm_lib/plc_comm/Melsec/__init__.py
makefortune_lib/comm_lib/plc_comm/Melsec/melsec.py
makefortune_lib/comm_lib/plc_comm/Snap_7/__init__.py
makefortune_lib/comm_lib/plc_comm/Snap_7/snap_7.py
makefortune_lib/comm_lib/plc_comm/modbusRTU/__init__.py
makefortune_lib/comm_lib/plc_comm/modbusRTU/modbusRTU.py
makefortune_lib/comm_lib/plc_comm/modbusTCP/__init__.py
makefortune_lib/comm_lib/plc_comm/modbusTCP/modbusTCP.py
makefortune_lib/device_lib/__init__.py
makefortune_lib/device_lib/Camera/__init__.py
makefortune_lib/device_lib/Camera/camera_factory.py
makefortune_lib/device_lib/Camera/HIKVISION/__init__.py
makefortune_lib/device_lib/Camera/HIKVISION/hik_2d_area_scan.py
makefortune_lib/device_lib/Camera/HIKVISION/hik_2d_line_scan.py
makefortune_lib/device_lib/Camera/HIKVISION/hk/CamOperation_class.py
makefortune_lib/device_lib/Camera/HIKVISION/hk/CameraParams_const.py
makefortune_lib/device_lib/Camera/HIKVISION/hk/CameraParams_header.py
makefortune_lib/device_lib/Camera/HIKVISION/hk/MvCameraControl_class.py
makefortune_lib/device_lib/Camera/HIKVISION/hk/MvCameraControl_header.py
makefortune_lib/device_lib/Camera/HIKVISION/hk/MvErrorDefine_const.py
makefortune_lib/device_lib/Camera/HIKVISION/hk/PixelType_const.py
makefortune_lib/device_lib/Camera/HIKVISION/hk/PixelType_header.py
makefortune_lib/device_lib/Camera/HIKVISION/hk/__init__.py
makefortune_lib/device_lib/Camera/Huaray/__init__.py
makefortune_lib/device_lib/Camera/Huaray/huaray2d/__init__.py
makefortune_lib/device_lib/Camera/Huaray/huaray2d/IMV/__init__.py
makefortune_lib-1.0.0.dist-info/METADATA
makefortune_lib-1.0.0.dist-info/WHEEL
makefortune_lib-1.0.0.dist-info/top_level.txt
makefortune_lib-1.0.0.dist-info/RECORD
