Metadata-Version: 2.1
Name: makefortune_lib
Version: 1.0.0
Summary: vision lib for myself
Author: Yichen Guo
License: MIT License
Classifier: Development Status :: 3 - Alpha
Classifier: Intended Audience :: Developers
Classifier: Topic :: Software Development :: Build Tools
Classifier: License :: OSI Approved :: MIT License
Classifier: Programming Language :: Python :: 3.8
Requires-Python: >=3.8
Requires-Dist: opencv-python>=4.5.3.56
Requires-Dist: numpy>=1.22.3
Requires-Dist: fins==1.0.5
Requires-Dist: pylogix
Requires-Dist: pymelsec
Requires-Dist: modbus-tk
Requires-Dist: pyserial
Requires-Dist: pyModbusTCP
Requires-Dist: python-snap7
Requires-Dist: matplotlib
